yputils/__init__.py
yputils/cfgs.py
yputils/file.py
yputils/pdf.py
yputils-0.7.1.dist-info/LICENSE
yputils-0.7.1.dist-info/METADATA
yputils-0.7.1.dist-info/WHEEL
yputils-0.7.1.dist-info/top_level.txt
yputils-0.7.1.dist-info/RECORD
