Metadata-Version: 2.1
Name: yputils
Version: 0.7.1
Summary: Python code segment for myself using.
Home-page: https://www.github.com/RyanLuDev/yputils
Author: Ryan Lu
Author-email: lyydev@gmail.com
Classifier: Programming Language :: Python :: 3
Classifier: License :: OSI Approved :: MIT License
Classifier: Operating System :: OS Independent
License-File: LICENSE
